{"schema": {"fields":[{"name":"genre","type":"string"},{"name":"size","type":"integer"}],"primaryKey":["genre"],"pandas_version":"0.20.0"}, "data": [{"genre":"Ancient-Cos","size":5},{"genre":"Sci-Fi","size":38},{"genre":"action","size":90},{"genre":"adventure","size":63},{"genre":"affectional","size":74},{"genre":"biographical","size":9},{"genre":"cartoon","size":56},{"genre":"comedy","size":115},{"genre":"crime","size":45},{"genre":"disaster","size":5},{"genre":"documentary","size":12},{"genre":"dracula","size":30},{"genre":"erotic","size":1},{"genre":"family","size":28},{"genre":"fantasy","size":46},{"genre":"historical","size":14},{"genre":"horror","size":57},{"genre":"musical","size":8},{"genre":"scenario","size":126},{"genre":"sports","size":4},{"genre":"suspense","size":48},{"genre":"swordsmen","size":4},{"genre":"war","size":19},{"genre":"western","size":2}]}